LICENSE
MANIFEST.in
README.md
requirements.txt
setup.py
rmageddon/__init__.py
rmageddon/builder.py
rmageddon/lint.py
rmageddon/validation.py
rmageddon.egg-info/PKG-INFO
rmageddon.egg-info/SOURCES.txt
rmageddon.egg-info/dependency_links.txt
rmageddon.egg-info/requires.txt
rmageddon.egg-info/top_level.txt
scripts/rmageddon