Metadata-Version: 1.0
Name: rmageddon
Version: 0.3.0
Summary: Small linting and building tool for R containers at QBiC
Home-page: UNKNOWN
Author: Sven Fillinger
Author-email: sven.fillinger@qbic.uni-tuebingen.de
License: MIT License
